{'id': 137012579, 'user_id': 1413177455, 'title': '心里向阳:12月9日复盘', 'text': '<p>一、周五盘面分析</p><p>周五，沪深两市震荡上涨。截止收盘，沪指涨0.43%报2912.01点，深成指涨0.81%报9878.62点，创业板指涨0.99%报1726.80点。两市共计成交4098亿元，较上个交易日减少140亿元。盘面上，智能音箱、无线耳机、消费电子等板块涨幅居前；丙烯酸、汽车整车、燃料电池等板块跌幅居前。</p><p>龙虎榜上，营业部资金净买入前三的是奋达科技（002681）、锦鸡股份（300798）、拉卡拉（300733），金额分别是0.84亿元、0.82亿元、0.67亿元。奋达科技买入金额最大的前5名，买入总计13908.07万元，占总成交比例16.94%。消息面上，三星或推出GalaxyBud+无线耳机，奋达科技触及涨停。公司在互动平台明确表示生产销售无线耳机。公司于近日接到公司控股股东肖奋及其一致行动人已合计减持2101万股的通知。</p><p> </p><p>二、盘中主要热点题材</p><p>1、  无线耳机：漫步者、雷柏科技、超华科技、共达电声、奋达科技、上海天洋、科森科技</p><p>2、  传媒娱乐</p><p>游戏：盛天网络、祥源文化、长城动漫、鼎龙文化</p><p> </p><p>三、游资和机构龙虎榜</p><p>瑞达期货（002961）：一机构买513万</p><p>广电计量（002967）：一机构买1154万</p><p>拉卡拉（300773）：华泰无锡梁清路游资封板，二机构买2747万</p><p>奋达科技（002681）：财通杭州上塘路游资封板，一机构买1336万</p><p>北京君正（300223）：国君南京太平南路游资封板，一机构买1652万</p><p>水晶光电（002273）：方正上海保定路游资封板，二机构买7277万，卖3348万</p><p>共达电声（002655）：华鑫上海自贸区及财通临安西苑路游资封板，二机构卖3210万</p><p>万通智控（300643）：华鑫湖州劳动路及中金无锡清扬路游资封板，一机构卖2342万</p><p>招商轮船（601872）：华泰上海武定路及国君上海福山路游资封板，二机构卖2133万</p><p>漫步者（002351）：海通蚌埠中荣街及华鑫南昌红谷中大道游资封板，三机构卖1.24亿</p><p>南宁百货（600712）：财富南京新模范马路及申港上海世纪大道游资封板</p><p>鼎龙文化（002502）：方正上海杨高南路及国海北京和平大街游资封板</p><p>祥源文化（600576）：华泰成都天府大道及兴业厦门杏林湾路游资封板</p><p>锦鸡股份（300789）：华泰上海武定路及华泰上海共和新路游资封板</p><p>飞亚达A（000026）：中信上海曹溪北路及国君成都双庆路游资封板</p><p>长城动漫（000835）：海通上海福州路及东莞北京分公司游资封板</p><p>合肥百货（000417）：宏信西昌月海路及银河宁波君子街游资封板</p><p>华晨装备（300809）：长江武汉武珞路及长城仙桃钱沟路游资封板</p><p>华西股份（000936）：国金成都武成大街及广发东莞虎门游资封板</p><p>当代东方（000673）：国盛宁波桑田路及国君上海江苏路游资封板</p><p>【公告淘金】</p><p>&gt;中恒集团（600252）控股股东广投集团计划增持2%-4.38%股份。</p><p>&gt;华英农业（002321）拟不超4.4亿元增资奥盛实业，并取得实际控制权。</p><p>&gt;永新股份（002014）拟3亿元投建年产33000吨新型BOPE薄膜项目。</p><p>&gt;华兴源创（688001）拟11.5亿元收购欧立通100%股权。</p><p>&gt;华电重工（601226）拟4.15亿元收购郑机院100%股权。郑机院在气膜建筑工业化系统、新建热源、常规电厂供热工程、长距离供热等城市和企业热力供应等业务领域拥有客户和技术积累。</p><p>&gt;青岛中程（300208）获荟金投资举牌。此次增持后，荟金投资通过荟金1号基金、荟金2号基金累计持有公司股份37,473,805股，占公司总股本的5%。</p><p> <a href="http://xueqiu.com/k?q=%23%E5%A4%8D%E7%9B%98%23" target="_blank">#复盘#</a>  <a href="http://xueqiu.com/k?q=%23%E8%B5%84%E8%AE%AF%E6%B7%98%E9%87%91%23" target="_blank">#资讯淘金#</a>  <a href="http://xueqiu.com/k?q=%23%E8%82%A1%E7%A5%A8%E5%BC%80%E6%88%B7%E5%93%AA%E5%AE%B6%E5%BC%BA%23" target="_blank">#股票开户哪家强#</a> </p><img class="ke_img" src="https://xqimg.imedao.com/16ee5db41c267823fe306fc2.jpg!custom.jpg" />', 'created_at': 1575814388000, 'retweet_count': 0, 'reply_count': 0, 'fav_count': 0, 'truncated': False, 'commentId': 0, 'retweet_status_id': 0, 'symbol_id': None, 'description': '一、周五盘面分析<br/>周五，沪深两市震荡上涨。截止收盘，沪指涨0.43%报2912.01点，深成指涨0.81%报9878.62点，创业板指涨0.99%报1726.80点。两市共计成交4098亿元，较上个交易日减少140亿元。盘面上，智能音箱、无线耳机、消费电子等板块涨幅居前；丙烯酸、汽车整车、燃料电池等板块跌幅居前。<b...', 'type': '3', 'source_link': 'http://xueqiu.com/about/mobile-xueqiu', 'edited_at': None, 'pic': 'https://xqimg.imedao.com/16ee5db41c267823fe306fc2.jpg!thumb.jpg', 'user': {'subscribeable': False, 'remark': None, 'status': 0, 'common_count': 0, 'friends_count': 159, 'recommend': None, 'st_color': '1', 'intro': None, 'stock_status_count': None, 'follow_me': False, 'allow_all_stock': False, 'stocks_count': None, 'domain': None, 'description': '', 'type': '1', 'location': None, 'id': 1413177455, 'url': None, 'screen_name': '心里向阳', 'following': False, 'blocking': False, 'profile': '/1413177455', 'verified': False, 'followers_count': 12291, 'donate_count': 0, 'verified_description': '', 'province': '', 'city': '', 'gender': 'n', 'status_count': 125, 'step': 'null', 'blog_description': None, 'verified_type': 0, 'last_status_id': 206635348, 'stats': None, 'name': None, 'group_ids': None, 'name_pinyin': None, 'screenname_pinyin': None, 'block_status': 0, '_source': None, 'profile_image_url': 'community/20197/1565259049731-1565259049908.jpg,community/20197/1565259049731-1565259049908.jpg!180x180.png,community/20197/1565259049731-1565259049908.jpg!50x50.png,community/20197/1565259049731-1565259049908.jpg!30x30.png', 'photo_domain': '//xavatar.imedao.com/', 'verified_realname': False, 'verified_infos': [{'data': None, 'verified_type': '5', 'verified_desc': '用户已完成实名身份认证'}]}, 'retweeted_status': None, 'target': '/1413177455/137012579', 'fragment': None, 'blocked': False, 'blocking': False, 'topic_pic': None, 'topic_symbol': None, 'topic_title': None, 'topic_desc': None, 'donate_count': 0, 'donate_snowcoin': 0, 'view_count': 0, 'offer': None, 'mark': 0, 'comment': None, 'expend': True, 'rqtype': None, 'rqid': 0, 'firstImg': 'https://xqimg.imedao.com/16ee5db41c267823fe306fc2.jpg!thumb.jpg', 'card': {'param': 'typ=MANUAL&id=2255,27213,70343', 'data': '{"items":[{"id":2255,"tag":"#复盘#","content":"","pic":"","backgroundColor":"","following":false,"pic_size":null,"status_count":2769,"follower_count":0},{"id":27213,"tag":"#资讯淘金#","content":"","pic":"","backgroundColor":"","following":false,"pic_size":null,"status_count":67,"follower_count":0},{"id":70343,"tag":"#股票开户哪家强#","content":"","pic":"","backgroundColor":"","following":false,"pic_size":null,"status_count":48,"follower_count":0}]}', 'first': '{"items":[{"id":2255,"tag":"#复盘#","content":"","pic":"","backgroundColor":"","following":false,"pic_size":null,"status_count":2769,"follower_count":0}]}', 'type': 'hashtag'}, 'favorited': False, 'favorited_created_at': None, 'topic_pic_thumbnail_small': None, 'topic_pic_thumbnail': None, 'topic_pic_headOrPad': None, 'canEdit': True, 'timeBefore': '2019-12-08 22:13', 'shortStatusMultiPic': False, 'mark_desc': None, 'reward_count': 0, 'reward_user_count': 0, 'paid_mention': None, 'is_answer': False, 'is_refused': False, 'is_reward': True, '_source': 'sc_5:6:SZ300798', 'pic_sizes': [{'width': 2048, 'height': 1324, 'ratio': '1.55', 'score': 0, 'setWidth': True, 'setHeight': True, 'setRatio': True, 'setScore': True}], 'like_count': 1, 'liked': False, 'promotion_pic': None, 'promotion_url': None, 'promotion_id': 0, 'quote_cards': None, 'is_ss_multi_pic': False, 'excellent_comments': None, 'is_bonus': False, 'source': 'iPhone', 'url': 'https://xueqiu.com/1413177455/137012579'}
