{'id': 220340350, 'user_id': 9884300041, 'title': '【光伏】欧盟将发布新一轮绿色能源计划', 'text': '<p><b>事件一：欧盟或再次提高2030年可再生能源目标。据机构预期，欧盟委员会将于周三公布一项绿色能源的计划，旨在加快欧洲推进清洁能源的步伐，尽快摆脱对俄罗斯化石燃料的依赖。</b></p><p>该计划主要有以下几个内容：</p><p>1）再次提高2030年可再生能源的目标。到 2030&nbsp;年，可再生能源的份额达到 45%，取代目前 40%&nbsp;的提议，此前刚从32%提升到40%。</p><p>2）路线图正在制定之中。其中屋顶翻新计划，提及&#34;到25年所有适宜的公共建筑均安装光伏&#34;；强制新建筑物安装光伏屋顶，缩短审批流程期限在三个月内；成立欧洲光伏产业联盟，预计到2030年欧洲累计光伏装机1000GW。</p><p>据统计，截至 2021年底，欧洲累计太阳能发电装机为 164.9 GW。那么在接下来的2022年-2030年期间预计每年新增装机量约92.8GW，那么复合增长率达到22%。</p><p><img src="https://xqimg.imedao.com/180d9e82602f3763fea9796b.png" class="ke_img" ></p><p><b>事件二：天然气等能源价格持续高位。能源价格层面，受俄乌局势持续影响，石油、天然气价格持续处于高位，导致欧洲能源局势比较紧张。</b></p><p>从最新天然气期货连续指数(NG0Y)来看，天然气盘面价格较去年增幅达到176%。石油价格来看，美原油期货指数同比上涨幅度达71.6%，目前到111美元附近，处于2014年以来新高。</p><p>欧洲能源价格暴涨的主要原因一方面来自于欧洲能源对外依存度高达60%，必须依赖外界能源的输入；另一方面欧洲天然气发电占比近20%，可再生能源占比接近35%，这些导致欧洲对天然气需求高，以及新能源电力供应不稳定。因而一旦国际局势不稳定，会导致原油、天然气等大宗价格大涨，那么欧洲的能源价格将不可避免地大幅上涨。</p><p>总的来看，此次紧张的国际局势让欧洲当局意识到其能源安全的重要性。为了摆脱其对俄罗斯等国家的能源依赖，欧洲转向清洁能源将是大趋势，未来光伏新增装机增量确定性高。另一方面，考虑到中国在光伏产业链具备全球绝对优势，硅料、硅片、电池片、组件各环节全球产能占比均在80-90%左右，将受益于欧洲新能源建设进度加快。</p><p><b>受益分支梳理</b></p><p><b>光伏产业链海外营收占比梳理：主环节中组件&gt;逆变器&gt;辅材，辅材环节中光伏支架&gt;光伏玻璃&gt;光伏胶膜。</b></p><p>2021年度是欧洲光伏的历史最好年份，全年新增光伏装机25.9GW，当前的总装机为164.9GW。全球对比来看，中国是新增光伏装机第一的地区，2021年新增装机量达54.8GW,占全球2021年新增装机量的32.3%左右。而欧洲新增26GW左右，与美国新增装机量接近，是光伏新增装机量世界前三，远高于第四位的印度13GW左右的装机量。在光伏各环节中，组件和逆变器是主要的出口环节。据光伏协会统计，2021年硅片、电池片、组件的出口总额达到284.3亿美元，其中硅片24.5亿美元、电池片13.7亿美元、组件246.1亿美元，分别占比8.6%、4.8%、86.6%。</p><p>1）组件环节：海外营收占比主要约33%-78%。组件是光伏电池主环节中主要出口的形式。其中一线组件海外营收占比占比大于非一线组件。</p><p>一线组件中，海外营收占比排序分别是晶科能源、天合光能、晶澳科技、隆基绿能。晶科能源：海外78%，欧洲18.4%，北美16%；天合光能：海外63%，欧洲20%，美国10.5%；晶澳科技：海外60.8%；隆基股份：海外47%，欧洲14%，美洲16%；</p><p>二三线组件中，海外营收占比顺序分别是东方日升、爱康科技、中来股份。东方日升海外占比58%；爱康科技海外营收占比47%；中来股份海外占比33%；</p><p>2）逆变器环节：海外营收占比约30-64%。固德威：海外64%；锦浪科技：海外54%；禾迈股份：海外55%；阳光电源：海外38%；德业股份：海外30%；</p><p>3）辅材环节：光伏支架&gt;光伏玻璃&gt;光伏胶膜。光伏支架-清源股份：海外68%；中信博：海外35%。光伏玻璃-福莱特：海外27%；光伏胶膜-福斯特：海外18%；海优新材：海外5%；银浆：帝科股份&nbsp;海外3%、苏州固锝&nbsp;海外30%；金刚线：美畅股份海外2%、高测股份2%；碳碳热场：金博股份1%。</p><p>来源：研讯社</p><p><a href="http://xueqiu.com/k?q=%23%E5%80%BA%E5%9F%BA%E5%A4%A7%E7%83%AD%EF%BC%81%E4%B8%80%E5%A4%A7%E6%89%B9%E5%80%BA%E5%9F%BA%E5%8F%91%E5%B8%83%E2%80%9C%E5%A4%A7%E9%A2%9D%E9%99%90%E8%B4%AD%E4%BB%A4%E2%80%9D%23" target="_blank">#债基大热！一大批债基发布“大额限购令”#</a>&nbsp;<a href="http://xueqiu.com/k?q=%23%E8%85%BE%E8%AE%AFQ1%E8%B0%83%E6%95%B4%E5%90%8E%E5%87%80%E5%88%A9255%E4%BA%BF%23" target="_blank">#腾讯Q1调整后净利255亿#</a>&nbsp;</p><p><a href="http://xueqiu.com/S/SZ002518" target="_blank">$科士达(SZ002518)$</a>&nbsp;<a href="http://xueqiu.com/S/SH688516" target="_blank">$奥特维(SH688516)$</a>&nbsp;<a href="http://xueqiu.com/S/SH601865" target="_blank">$福莱特(SH601865)$</a>&nbsp;</p><p>风险提示：如需购买相关基金产品，请您关注投资者适当性管理相关规定，提前做好风险测评，并根据您自身的风险承受能力购买与之相匹配的风险等级的基金产品。基金的过往业绩并不预示其未来表现，基金管理人管理的其他基金的业绩并不构成基金业绩表现的保证。基金投资需注意投资风险，请仔细阅读基金合同和基金招募说明书，了解基金的具体情况。</p>', 'created_at': 1652923392000, 'retweet_count': 1, 'reply_count': 0, 'fav_count': 4, 'truncated': False, 'commentId': 0, 'retweet_status_id': 0, 'symbol_id': None, 'description': '事件一：欧盟或再次提高2030年可再生能源目标。据机构预期，欧盟委员会将于周三公布一项绿色能源的计划，旨在加快欧洲推进清洁能源的步伐，尽快摆脱对俄罗斯化石燃料的依赖。<br/>该计划主要有以下几个内容：<br/>1）再次提高2030年可再生能源的目标。到 2030 年，可再生能源的份额达到 45%，取代...', 'type': '3', 'source_link': None, 'edited_at': None, 'pic': 'https://xqimg.imedao.com/180d9e82602f3763fea9796b.png', 'user': {'subscribeable': False, 'remark': None, 'status': 1, 'common_count': 0, 'friends_count': 1169, 'recommend': None, 'st_color': '1', 'intro': None, 'stock_status_count': None, 'follow_me': False, 'allow_all_stock': False, 'stocks_count': None, 'domain': None, 'description': '光伏ETF(515790)――老牌ETF王牌团队华泰柏瑞指数投资天团最新产品，团队开展ETF业务以来十四年零差错运营，多年来共计斩获11尊金牛、10项金基金大奖，跟踪误差水平行业领先。\n\n内外兼修懂投资，小光人美颜值高，光伏产业全覆盖，小光在线等你撩~爱上小光，和小光一起关注光伏ETF吧o(*￣￣*)ブ~', 'type': '7', 'stats': None, 'location': None, 'id': 9884300041, 'url': None, 'screen_name': '光伏ETF_', 'following': False, 'blocking': False, 'profile': '/9884300041', 'verified': True, 'followers_count': 8724, 'donate_count': 0, 'verified_description': '华泰柏瑞基金管理有限公司官方账号', 'province': '上海', 'city': '不限', 'gender': 'n', 'step': 'null', 'blog_description': None, 'verified_type': 3, 'last_status_id': 227311868, 'status_count': 1941, 'name': None, 'group_ids': None, 'name_pinyin': None, 'screenname_pinyin': None, 'block_status': 0, '_source': None, 'profile_image_url': 'community/202010/1605603026775-1605603030469.png,community/202010/1605603026775-1605603030469.png!180x180.png,community/202010/1605603026775-1605603030469.png!50x50.png,community/202010/1605603026775-1605603030469.png!30x30.png', 'photo_domain': '//xavatar.imedao.com/', 'verified_realname': False, 'verified_infos': [{'data': None, 'verified_type': '4', 'verified_desc': '华泰柏瑞基金管理有限公司官方账号'}]}, 'retweeted_status': None, 'target': '/9884300041/220340350', 'fragment': None, 'blocked': False, 'blocking': False, 'topic_pic': None, 'topic_symbol': None, 'topic_title': None, 'topic_desc': None, 'donate_count': 0, 'donate_snowcoin': 0, 'view_count': 0, 'offer': None, 'mark': 0, 'comment': None, 'expend': True, 'rqtype': None, 'rqid': 0, 'firstImg': 'https://xqimg.imedao.com/180d9e82602f3763fea9796b.png', 'card': {'param': 'typ=OP&id=229176,229081', 'data': '{"items":[{"id":229176,"tag":"#债基大热！一大批债基发布“大额限购令”#","content":"今年债权类基金“大热”！今日又有多只纯债基金公告暂停大额申购。5月以来，已有超130只债基发布“大额限购令”。","pic":"https://xqimg.imedao.com/180d9d83731f3ed3fe2d05f2.png","backgroundColor":"","following":false,"pic_size":null,"status_count":128,"follower_count":0},{"id":229081,"tag":"#腾讯Q1调整后净利255亿#","content":"腾讯控股：第一季度营收1355亿元，上年同期1353亿元；第一季度调整后净利润255亿元人民币，同比下降23%。","pic":"https://xqimg.imedao.com/180d661518de2cc3fed86481.png","backgroundColor":"","following":false,"pic_size":null,"status_count":161,"follower_count":0}]}', 'first': '{"items":[{"id":229176,"tag":"#债基大热！一大批债基发布“大额限购令”#","content":"今年债权类基金“大热”！今日又有多只纯债基金公告暂停大额申购。5月以来，已有超130只债基发布“大额限购令”。","pic":"https://xqimg.imedao.com/180d9d83731f3ed3fe2d05f2.png","backgroundColor":"","following":false,"pic_size":null,"status_count":128,"follower_count":0}]}', 'type': 'hashtag'}, 'favorited': False, 'favorited_created_at': None, 'topic_pic_headOrPad': None, 'topic_pic_thumbnail_small': None, 'topic_pic_thumbnail': None, 'canEdit': True, 'timeBefore': '05-19 09:23', 'shortStatusMultiPic': False, 'mark_desc': None, 'reward_count': 0, 'reward_user_count': 0, 'paid_mention': None, 'is_answer': False, 'is_refused': False, 'is_reward': True, '_source': 'sc_3:8:SH601865', 'pic_sizes': [{'width': 640, 'height': 426, 'ratio': '1.50', 'score': 0, 'setWidth': True, 'setHeight': True, 'setRatio': True, 'setScore': True}], 'like_count': 6, 'liked': False, 'promotion_pic': None, 'promotion_url': None, 'promotion_id': 0, 'quote_cards': None, 'is_ss_multi_pic': False, 'excellent_comments': None, 'is_bonus': False, 'source': '雪球', 'url': 'https://xueqiu.com/9884300041/220340350'}
{'id': 220340350, 'user_id': 9884300041, 'title': '【光伏】欧盟将发布新一轮绿色能源计划', 'text': '<p><b>事件一：欧盟或再次提高2030年可再生能源目标。据机构预期，欧盟委员会将于周三公布一项绿色能源的计划，旨在加快欧洲推进清洁能源的步伐，尽快摆脱对俄罗斯化石燃料的依赖。</b></p><p>该计划主要有以下几个内容：</p><p>1）再次提高2030年可再生能源的目标。到 2030&nbsp;年，可再生能源的份额达到 45%，取代目前 40%&nbsp;的提议，此前刚从32%提升到40%。</p><p>2）路线图正在制定之中。其中屋顶翻新计划，提及&#34;到25年所有适宜的公共建筑均安装光伏&#34;；强制新建筑物安装光伏屋顶，缩短审批流程期限在三个月内；成立欧洲光伏产业联盟，预计到2030年欧洲累计光伏装机1000GW。</p><p>据统计，截至 2021年底，欧洲累计太阳能发电装机为 164.9 GW。那么在接下来的2022年-2030年期间预计每年新增装机量约92.8GW，那么复合增长率达到22%。</p><p><img src="https://xqimg.imedao.com/180d9e82602f3763fea9796b.png" class="ke_img" ></p><p><b>事件二：天然气等能源价格持续高位。能源价格层面，受俄乌局势持续影响，石油、天然气价格持续处于高位，导致欧洲能源局势比较紧张。</b></p><p>从最新天然气期货连续指数(NG0Y)来看，天然气盘面价格较去年增幅达到176%。石油价格来看，美原油期货指数同比上涨幅度达71.6%，目前到111美元附近，处于2014年以来新高。</p><p>欧洲能源价格暴涨的主要原因一方面来自于欧洲能源对外依存度高达60%，必须依赖外界能源的输入；另一方面欧洲天然气发电占比近20%，可再生能源占比接近35%，这些导致欧洲对天然气需求高，以及新能源电力供应不稳定。因而一旦国际局势不稳定，会导致原油、天然气等大宗价格大涨，那么欧洲的能源价格将不可避免地大幅上涨。</p><p>总的来看，此次紧张的国际局势让欧洲当局意识到其能源安全的重要性。为了摆脱其对俄罗斯等国家的能源依赖，欧洲转向清洁能源将是大趋势，未来光伏新增装机增量确定性高。另一方面，考虑到中国在光伏产业链具备全球绝对优势，硅料、硅片、电池片、组件各环节全球产能占比均在80-90%左右，将受益于欧洲新能源建设进度加快。</p><p><b>受益分支梳理</b></p><p><b>光伏产业链海外营收占比梳理：主环节中组件&gt;逆变器&gt;辅材，辅材环节中光伏支架&gt;光伏玻璃&gt;光伏胶膜。</b></p><p>2021年度是欧洲光伏的历史最好年份，全年新增光伏装机25.9GW，当前的总装机为164.9GW。全球对比来看，中国是新增光伏装机第一的地区，2021年新增装机量达54.8GW,占全球2021年新增装机量的32.3%左右。而欧洲新增26GW左右，与美国新增装机量接近，是光伏新增装机量世界前三，远高于第四位的印度13GW左右的装机量。在光伏各环节中，组件和逆变器是主要的出口环节。据光伏协会统计，2021年硅片、电池片、组件的出口总额达到284.3亿美元，其中硅片24.5亿美元、电池片13.7亿美元、组件246.1亿美元，分别占比8.6%、4.8%、86.6%。</p><p>1）组件环节：海外营收占比主要约33%-78%。组件是光伏电池主环节中主要出口的形式。其中一线组件海外营收占比占比大于非一线组件。</p><p>一线组件中，海外营收占比排序分别是晶科能源、天合光能、晶澳科技、隆基绿能。晶科能源：海外78%，欧洲18.4%，北美16%；天合光能：海外63%，欧洲20%，美国10.5%；晶澳科技：海外60.8%；隆基股份：海外47%，欧洲14%，美洲16%；</p><p>二三线组件中，海外营收占比顺序分别是东方日升、爱康科技、中来股份。东方日升海外占比58%；爱康科技海外营收占比47%；中来股份海外占比33%；</p><p>2）逆变器环节：海外营收占比约30-64%。固德威：海外64%；锦浪科技：海外54%；禾迈股份：海外55%；阳光电源：海外38%；德业股份：海外30%；</p><p>3）辅材环节：光伏支架&gt;光伏玻璃&gt;光伏胶膜。光伏支架-清源股份：海外68%；中信博：海外35%。光伏玻璃-福莱特：海外27%；光伏胶膜-福斯特：海外18%；海优新材：海外5%；银浆：帝科股份&nbsp;海外3%、苏州固锝&nbsp;海外30%；金刚线：美畅股份海外2%、高测股份2%；碳碳热场：金博股份1%。</p><p>来源：研讯社</p><p><a href="http://xueqiu.com/k?q=%23%E5%80%BA%E5%9F%BA%E5%A4%A7%E7%83%AD%EF%BC%81%E4%B8%80%E5%A4%A7%E6%89%B9%E5%80%BA%E5%9F%BA%E5%8F%91%E5%B8%83%E2%80%9C%E5%A4%A7%E9%A2%9D%E9%99%90%E8%B4%AD%E4%BB%A4%E2%80%9D%23" target="_blank">#债基大热！一大批债基发布“大额限购令”#</a>&nbsp;<a href="http://xueqiu.com/k?q=%23%E8%85%BE%E8%AE%AFQ1%E8%B0%83%E6%95%B4%E5%90%8E%E5%87%80%E5%88%A9255%E4%BA%BF%23" target="_blank">#腾讯Q1调整后净利255亿#</a>&nbsp;</p><p><a href="http://xueqiu.com/S/SZ002518" target="_blank">$科士达(SZ002518)$</a>&nbsp;<a href="http://xueqiu.com/S/SH688516" target="_blank">$奥特维(SH688516)$</a>&nbsp;<a href="http://xueqiu.com/S/SH601865" target="_blank">$福莱特(SH601865)$</a>&nbsp;</p><p>风险提示：如需购买相关基金产品，请您关注投资者适当性管理相关规定，提前做好风险测评，并根据您自身的风险承受能力购买与之相匹配的风险等级的基金产品。基金的过往业绩并不预示其未来表现，基金管理人管理的其他基金的业绩并不构成基金业绩表现的保证。基金投资需注意投资风险，请仔细阅读基金合同和基金招募说明书，了解基金的具体情况。</p>', 'created_at': 1652923392000, 'retweet_count': 1, 'reply_count': 0, 'fav_count': 4, 'truncated': False, 'commentId': 0, 'retweet_status_id': 0, 'symbol_id': None, 'description': '事件一：欧盟或再次提高2030年可再生能源目标。据机构预期，欧盟委员会将于周三公布一项绿色能源的计划，旨在加快欧洲推进清洁能源的步伐，尽快摆脱对俄罗斯化石燃料的依赖。<br/>该计划主要有以下几个内容：<br/>1）再次提高2030年可再生能源的目标。到 2030 年，可再生能源的份额达到 45%，取代...', 'type': '3', 'source_link': None, 'edited_at': None, 'pic': 'https://xqimg.imedao.com/180d9e82602f3763fea9796b.png', 'user': {'subscribeable': False, 'remark': None, 'status': 1, 'common_count': 0, 'friends_count': 1169, 'recommend': None, 'st_color': '1', 'intro': None, 'stock_status_count': None, 'follow_me': False, 'allow_all_stock': False, 'stocks_count': None, 'domain': None, 'description': '光伏ETF(515790)――老牌ETF王牌团队华泰柏瑞指数投资天团最新产品，团队开展ETF业务以来十四年零差错运营，多年来共计斩获11尊金牛、10项金基金大奖，跟踪误差水平行业领先。\n\n内外兼修懂投资，小光人美颜值高，光伏产业全覆盖，小光在线等你撩~爱上小光，和小光一起关注光伏ETF吧o(*￣￣*)ブ~', 'stats': None, 'type': '7', 'location': None, 'id': 9884300041, 'url': None, 'screen_name': '光伏ETF_', 'following': False, 'blocking': False, 'profile': '/9884300041', 'verified': True, 'followers_count': 8724, 'donate_count': 0, 'verified_description': '华泰柏瑞基金管理有限公司官方账号', 'province': '上海', 'city': '不限', 'gender': 'n', 'step': 'null', 'blog_description': None, 'verified_type': 3, 'last_status_id': 227311868, 'status_count': 1941, 'name': None, 'group_ids': None, 'name_pinyin': None, 'screenname_pinyin': None, 'block_status': 0, '_source': None, 'profile_image_url': 'community/202010/1605603026775-1605603030469.png,community/202010/1605603026775-1605603030469.png!180x180.png,community/202010/1605603026775-1605603030469.png!50x50.png,community/202010/1605603026775-1605603030469.png!30x30.png', 'photo_domain': '//xavatar.imedao.com/', 'verified_realname': False, 'verified_infos': [{'data': None, 'verified_type': '4', 'verified_desc': '华泰柏瑞基金管理有限公司官方账号'}]}, 'retweeted_status': None, 'target': '/9884300041/220340350', 'fragment': None, 'blocked': False, 'blocking': False, 'topic_pic': None, 'topic_symbol': None, 'topic_title': None, 'topic_desc': None, 'donate_count': 0, 'donate_snowcoin': 0, 'view_count': 0, 'offer': None, 'mark': 0, 'comment': None, 'expend': True, 'rqtype': None, 'rqid': 0, 'firstImg': 'https://xqimg.imedao.com/180d9e82602f3763fea9796b.png', 'card': {'param': 'typ=OP&id=229176,229081', 'data': '{"items":[{"id":229176,"tag":"#债基大热！一大批债基发布“大额限购令”#","content":"今年债权类基金“大热”！今日又有多只纯债基金公告暂停大额申购。5月以来，已有超130只债基发布“大额限购令”。","pic":"https://xqimg.imedao.com/180d9d83731f3ed3fe2d05f2.png","backgroundColor":"","following":false,"pic_size":null,"status_count":128,"follower_count":0},{"id":229081,"tag":"#腾讯Q1调整后净利255亿#","content":"腾讯控股：第一季度营收1355亿元，上年同期1353亿元；第一季度调整后净利润255亿元人民币，同比下降23%。","pic":"https://xqimg.imedao.com/180d661518de2cc3fed86481.png","backgroundColor":"","following":false,"pic_size":null,"status_count":161,"follower_count":0}]}', 'first': '{"items":[{"id":229176,"tag":"#债基大热！一大批债基发布“大额限购令”#","content":"今年债权类基金“大热”！今日又有多只纯债基金公告暂停大额申购。5月以来，已有超130只债基发布“大额限购令”。","pic":"https://xqimg.imedao.com/180d9d83731f3ed3fe2d05f2.png","backgroundColor":"","following":false,"pic_size":null,"status_count":128,"follower_count":0}]}', 'type': 'hashtag'}, 'favorited': False, 'favorited_created_at': None, 'topic_pic_thumbnail': None, 'topic_pic_headOrPad': None, 'topic_pic_thumbnail_small': None, 'canEdit': True, 'timeBefore': '05-19 09:23', 'shortStatusMultiPic': False, 'mark_desc': None, 'reward_count': 0, 'reward_user_count': 0, 'paid_mention': None, 'is_answer': False, 'is_refused': False, 'is_reward': True, '_source': 'sc_2:9:SH601865', 'pic_sizes': [{'width': 640, 'height': 426, 'ratio': '1.50', 'score': 0, 'setWidth': True, 'setHeight': True, 'setRatio': True, 'setScore': True}], 'like_count': 6, 'liked': False, 'promotion_pic': None, 'promotion_url': None, 'promotion_id': 0, 'quote_cards': None, 'is_ss_multi_pic': False, 'excellent_comments': None, 'source': '雪球', 'is_bonus': False, 'url': 'https://xueqiu.com/9884300041/220340350'}
{'id': 220340350, 'user_id': 9884300041, 'title': '【光伏】欧盟将发布新一轮绿色能源计划', 'text': '<p><b>事件一：欧盟或再次提高2030年可再生能源目标。据机构预期，欧盟委员会将于周三公布一项绿色能源的计划，旨在加快欧洲推进清洁能源的步伐，尽快摆脱对俄罗斯化石燃料的依赖。</b></p><p>该计划主要有以下几个内容：</p><p>1）再次提高2030年可再生能源的目标。到 2030&nbsp;年，可再生能源的份额达到 45%，取代目前 40%&nbsp;的提议，此前刚从32%提升到40%。</p><p>2）路线图正在制定之中。其中屋顶翻新计划，提及&#34;到25年所有适宜的公共建筑均安装光伏&#34;；强制新建筑物安装光伏屋顶，缩短审批流程期限在三个月内；成立欧洲光伏产业联盟，预计到2030年欧洲累计光伏装机1000GW。</p><p>据统计，截至 2021年底，欧洲累计太阳能发电装机为 164.9 GW。那么在接下来的2022年-2030年期间预计每年新增装机量约92.8GW，那么复合增长率达到22%。</p><p><img src="https://xqimg.imedao.com/180d9e82602f3763fea9796b.png" class="ke_img" ></p><p><b>事件二：天然气等能源价格持续高位。能源价格层面，受俄乌局势持续影响，石油、天然气价格持续处于高位，导致欧洲能源局势比较紧张。</b></p><p>从最新天然气期货连续指数(NG0Y)来看，天然气盘面价格较去年增幅达到176%。石油价格来看，美原油期货指数同比上涨幅度达71.6%，目前到111美元附近，处于2014年以来新高。</p><p>欧洲能源价格暴涨的主要原因一方面来自于欧洲能源对外依存度高达60%，必须依赖外界能源的输入；另一方面欧洲天然气发电占比近20%，可再生能源占比接近35%，这些导致欧洲对天然气需求高，以及新能源电力供应不稳定。因而一旦国际局势不稳定，会导致原油、天然气等大宗价格大涨，那么欧洲的能源价格将不可避免地大幅上涨。</p><p>总的来看，此次紧张的国际局势让欧洲当局意识到其能源安全的重要性。为了摆脱其对俄罗斯等国家的能源依赖，欧洲转向清洁能源将是大趋势，未来光伏新增装机增量确定性高。另一方面，考虑到中国在光伏产业链具备全球绝对优势，硅料、硅片、电池片、组件各环节全球产能占比均在80-90%左右，将受益于欧洲新能源建设进度加快。</p><p><b>受益分支梳理</b></p><p><b>光伏产业链海外营收占比梳理：主环节中组件&gt;逆变器&gt;辅材，辅材环节中光伏支架&gt;光伏玻璃&gt;光伏胶膜。</b></p><p>2021年度是欧洲光伏的历史最好年份，全年新增光伏装机25.9GW，当前的总装机为164.9GW。全球对比来看，中国是新增光伏装机第一的地区，2021年新增装机量达54.8GW,占全球2021年新增装机量的32.3%左右。而欧洲新增26GW左右，与美国新增装机量接近，是光伏新增装机量世界前三，远高于第四位的印度13GW左右的装机量。在光伏各环节中，组件和逆变器是主要的出口环节。据光伏协会统计，2021年硅片、电池片、组件的出口总额达到284.3亿美元，其中硅片24.5亿美元、电池片13.7亿美元、组件246.1亿美元，分别占比8.6%、4.8%、86.6%。</p><p>1）组件环节：海外营收占比主要约33%-78%。组件是光伏电池主环节中主要出口的形式。其中一线组件海外营收占比占比大于非一线组件。</p><p>一线组件中，海外营收占比排序分别是晶科能源、天合光能、晶澳科技、隆基绿能。晶科能源：海外78%，欧洲18.4%，北美16%；天合光能：海外63%，欧洲20%，美国10.5%；晶澳科技：海外60.8%；隆基股份：海外47%，欧洲14%，美洲16%；</p><p>二三线组件中，海外营收占比顺序分别是东方日升、爱康科技、中来股份。东方日升海外占比58%；爱康科技海外营收占比47%；中来股份海外占比33%；</p><p>2）逆变器环节：海外营收占比约30-64%。固德威：海外64%；锦浪科技：海外54%；禾迈股份：海外55%；阳光电源：海外38%；德业股份：海外30%；</p><p>3）辅材环节：光伏支架&gt;光伏玻璃&gt;光伏胶膜。光伏支架-清源股份：海外68%；中信博：海外35%。光伏玻璃-福莱特：海外27%；光伏胶膜-福斯特：海外18%；海优新材：海外5%；银浆：帝科股份&nbsp;海外3%、苏州固锝&nbsp;海外30%；金刚线：美畅股份海外2%、高测股份2%；碳碳热场：金博股份1%。</p><p>来源：研讯社</p><p><a href="http://xueqiu.com/k?q=%23%E5%80%BA%E5%9F%BA%E5%A4%A7%E7%83%AD%EF%BC%81%E4%B8%80%E5%A4%A7%E6%89%B9%E5%80%BA%E5%9F%BA%E5%8F%91%E5%B8%83%E2%80%9C%E5%A4%A7%E9%A2%9D%E9%99%90%E8%B4%AD%E4%BB%A4%E2%80%9D%23" target="_blank">#债基大热！一大批债基发布“大额限购令”#</a>&nbsp;<a href="http://xueqiu.com/k?q=%23%E8%85%BE%E8%AE%AFQ1%E8%B0%83%E6%95%B4%E5%90%8E%E5%87%80%E5%88%A9255%E4%BA%BF%23" target="_blank">#腾讯Q1调整后净利255亿#</a>&nbsp;</p><p><a href="http://xueqiu.com/S/SZ002518" target="_blank">$科士达(SZ002518)$</a>&nbsp;<a href="http://xueqiu.com/S/SH688516" target="_blank">$奥特维(SH688516)$</a>&nbsp;<a href="http://xueqiu.com/S/SH601865" target="_blank">$福莱特(SH601865)$</a>&nbsp;</p><p>风险提示：如需购买相关基金产品，请您关注投资者适当性管理相关规定，提前做好风险测评，并根据您自身的风险承受能力购买与之相匹配的风险等级的基金产品。基金的过往业绩并不预示其未来表现，基金管理人管理的其他基金的业绩并不构成基金业绩表现的保证。基金投资需注意投资风险，请仔细阅读基金合同和基金招募说明书，了解基金的具体情况。</p>', 'created_at': 1652923392000, 'retweet_count': 1, 'reply_count': 0, 'fav_count': 4, 'truncated': False, 'commentId': 0, 'retweet_status_id': 0, 'symbol_id': None, 'description': '事件一：欧盟或再次提高2030年可再生能源目标。据机构预期，欧盟委员会将于周三公布一项绿色能源的计划，旨在加快欧洲推进清洁能源的步伐，尽快摆脱对俄罗斯化石燃料的依赖。<br/>该计划主要有以下几个内容：<br/>1）再次提高2030年可再生能源的目标。到 2030 年，可再生能源的份额达到 45%，取代...', 'type': '3', 'source_link': None, 'edited_at': None, 'pic': 'https://xqimg.imedao.com/180d9e82602f3763fea9796b.png', 'user': {'subscribeable': False, 'remark': None, 'status': 1, 'common_count': 0, 'friends_count': 1169, 'recommend': None, 'st_color': '1', 'intro': None, 'stock_status_count': None, 'follow_me': False, 'allow_all_stock': False, 'stocks_count': None, 'domain': None, 'description': '光伏ETF(515790)――老牌ETF王牌团队华泰柏瑞指数投资天团最新产品，团队开展ETF业务以来十四年零差错运营，多年来共计斩获11尊金牛、10项金基金大奖，跟踪误差水平行业领先。\n\n内外兼修懂投资，小光人美颜值高，光伏产业全覆盖，小光在线等你撩~爱上小光，和小光一起关注光伏ETF吧o(*￣￣*)ブ~', 'stats': None, 'type': '7', 'location': None, 'id': 9884300041, 'url': None, 'screen_name': '光伏ETF_', 'following': False, 'blocking': False, 'profile': '/9884300041', 'verified': True, 'followers_count': 8724, 'donate_count': 0, 'verified_description': '华泰柏瑞基金管理有限公司官方账号', 'province': '上海', 'city': '不限', 'gender': 'n', 'step': 'null', 'blog_description': None, 'verified_type': 3, 'last_status_id': 227311868, 'status_count': 1941, 'name': None, 'group_ids': None, 'name_pinyin': None, 'screenname_pinyin': None, 'block_status': 0, '_source': None, 'profile_image_url': 'community/202010/1605603026775-1605603030469.png,community/202010/1605603026775-1605603030469.png!180x180.png,community/202010/1605603026775-1605603030469.png!50x50.png,community/202010/1605603026775-1605603030469.png!30x30.png', 'photo_domain': '//xavatar.imedao.com/', 'verified_realname': False, 'verified_infos': [{'data': None, 'verified_type': '4', 'verified_desc': '华泰柏瑞基金管理有限公司官方账号'}]}, 'retweeted_status': None, 'target': '/9884300041/220340350', 'fragment': None, 'blocked': False, 'blocking': False, 'topic_pic': None, 'topic_symbol': None, 'topic_title': None, 'topic_desc': None, 'donate_count': 0, 'donate_snowcoin': 0, 'view_count': 0, 'offer': None, 'mark': 0, 'comment': None, 'expend': True, 'rqtype': None, 'rqid': 0, 'firstImg': 'https://xqimg.imedao.com/180d9e82602f3763fea9796b.png', 'card': {'param': 'typ=OP&id=229176,229081', 'data': '{"items":[{"id":229176,"tag":"#债基大热！一大批债基发布“大额限购令”#","content":"今年债权类基金“大热”！今日又有多只纯债基金公告暂停大额申购。5月以来，已有超130只债基发布“大额限购令”。","pic":"https://xqimg.imedao.com/180d9d83731f3ed3fe2d05f2.png","backgroundColor":"","following":false,"pic_size":null,"status_count":128,"follower_count":0},{"id":229081,"tag":"#腾讯Q1调整后净利255亿#","content":"腾讯控股：第一季度营收1355亿元，上年同期1353亿元；第一季度调整后净利润255亿元人民币，同比下降23%。","pic":"https://xqimg.imedao.com/180d661518de2cc3fed86481.png","backgroundColor":"","following":false,"pic_size":null,"status_count":161,"follower_count":0}]}', 'first': '{"items":[{"id":229176,"tag":"#债基大热！一大批债基发布“大额限购令”#","content":"今年债权类基金“大热”！今日又有多只纯债基金公告暂停大额申购。5月以来，已有超130只债基发布“大额限购令”。","pic":"https://xqimg.imedao.com/180d9d83731f3ed3fe2d05f2.png","backgroundColor":"","following":false,"pic_size":null,"status_count":128,"follower_count":0}]}', 'type': 'hashtag'}, 'favorited': False, 'favorited_created_at': None, 'topic_pic_thumbnail': None, 'topic_pic_headOrPad': None, 'topic_pic_thumbnail_small': None, 'canEdit': True, 'timeBefore': '05-19 09:23', 'shortStatusMultiPic': False, 'mark_desc': None, 'reward_count': 0, 'reward_user_count': 0, 'paid_mention': None, 'is_answer': False, 'is_refused': False, 'is_reward': True, '_source': 'sc_3:5:SH601865', 'pic_sizes': [{'width': 640, 'height': 426, 'ratio': '1.50', 'score': 0, 'setWidth': True, 'setHeight': True, 'setRatio': True, 'setScore': True}], 'like_count': 6, 'liked': False, 'promotion_pic': None, 'promotion_url': None, 'promotion_id': 0, 'quote_cards': None, 'is_ss_multi_pic': False, 'excellent_comments': None, 'source': '雪球', 'is_bonus': False, 'url': 'https://xueqiu.com/9884300041/220340350'}
